architextor/__init__.py
architextor/main.py
architextor/prompts.py
architextor-2025.12.20185502.dist-info/METADATA
architextor-2025.12.20185502.dist-info/WHEEL
architextor-2025.12.20185502.dist-info/top_level.txt
architextor-2025.12.20185502.dist-info/RECORD
