Metadata-Version: 2.4
Name: architextor
Version: 2025.12.20185502
Summary: A new package designed to process and interpret structured descriptions of neural network architectures from textual input. Users provide detailed text about an ANN's innate design, such as layer type
Author-email: architextor <hi@eugene.plus>
License: MIT
Project-URL: Homepage, https://github.com/chigwell/architextor
Requires-Python: >=3.9
Requires-Dist: langchain-llm7>=0.0.0
Requires-Dist: llmatch-messages>=0.0.0
Requires-Dist: langchain-core>=0.3.0
